irelia/__init__.py
irelia/esports_lib.py
irelia-0.0.8.dist-info/LICENSE
irelia-0.0.8.dist-info/METADATA
irelia-0.0.8.dist-info/WHEEL
irelia-0.0.8.dist-info/top_level.txt
irelia-0.0.8.dist-info/RECORD
