Metadata-Version: 2.1
Name: irelia
Version: 0.0.8
Summary: A lolesports api wrapper
Home-page: https://github.com/bgraver/Irelia
Author: Brandon Graver
Author-email: graver.brandon@gmail.com
License: UNKNOWN
Project-URL: Source, https://github.com/bgraver/Irelia
Project-URL: Original API, https://vickz84259.github.io/lolesports-api-docs/
Keywords: api,lol,league of legends,lolesports,esports,wrapper
Platform: UNKNOWN
Classifier: Development Status :: 3 - Alpha
Classifier: License :: OSI Approved :: MIT License
Classifier: Programming Language :: Python :: 3
Requires-Python: >=3
Requires-Dist: requests
